tempfox/__init__.py
tempfox/__main__.py
tempfox/core.py
tempfox-1.0.1.dist-info/METADATA
tempfox-1.0.1.dist-info/WHEEL
tempfox-1.0.1.dist-info/entry_points.txt
tempfox-1.0.1.dist-info/top_level.txt
tempfox-1.0.1.dist-info/RECORD
