Metadata-Version: 2.2
Name: tempfox
Version: 1.0.1
Summary: AWS Credential Manager and CloudFox Integration Tool
Author: David Diaz
License: MIT
Project-URL: Homepage, https://github.com/alfdav/tempfox
Project-URL: Repository, https://github.com/alfdav/tempfox
Classifier: Development Status :: 5 - Production/Stable
Classifier: Intended Audience :: Developers
Classifier: Intended Audience :: System Administrators
Classifier: Topic :: Security
Classifier: Topic :: System :: Systems Administration
Classifier: License :: OSI Approved :: MIT License
Classifier: Programming Language :: Python :: 3
Classifier: Programming Language :: Python :: 3.6
Classifier: Programming Language :: Python :: 3.7
Classifier: Programming Language :: Python :: 3.8
Classifier: Programming Language :: Python :: 3.9
Classifier: Programming Language :: Python :: 3.10
Classifier: Operating System :: OS Independent
Requires-Python: >=3.6
Requires-Dist: boto3>=1.26.0
